Arduino/__init__.py
Arduino/arduino.py
pyArduinoAPI-0.8.2.dist-info/METADATA
pyArduinoAPI-0.8.2.dist-info/WHEEL
pyArduinoAPI-0.8.2.dist-info/top_level.txt
pyArduinoAPI-0.8.2.dist-info/RECORD
