Metadata-Version: 2.1
Name: pyArduinoAPI
Version: 0.8.2
Summary: A light-weight Python library that provides a serial   bridge for communicating with Arduino microcontroller boards. Extended to work with Python 3
Home-page: https://github.com/pigeonburger/pyArduinoAPI
Author: Pigeonburger
Author-email: pigeonburger@pigeonburger.xyz
License: MIT
Platform: UNKNOWN
Requires-Dist: pyserial
